hq/__init__.py
hq/cli.py
hq/formatter.py
hq/parser.py
hq/query.py
hq_html-0.1.1.dist-info/METADATA
hq_html-0.1.1.dist-info/WHEEL
hq_html-0.1.1.dist-info/entry_points.txt
hq_html-0.1.1.dist-info/top_level.txt
hq_html-0.1.1.dist-info/RECORD
