Metadata-Version: 2.4
Name: hq-html
Version: 0.1.1
Summary: A command-line HTML processor inspired by jq
Author-email: JuleZ <julestblt.dev@pm.me>
License: MIT
Requires-Python: >=3.9
Requires-Dist: click>=8.0.0
Requires-Dist: beautifulsoup4>=4.12.0
Requires-Dist: lxml>=4.9.0
Requires-Dist: rich>=13.0.0
Requires-Dist: pygments>=2.15.0
Provides-Extra: dev
Requires-Dist: pytest>=7.0.0; extra == "dev"
Requires-Dist: black>=23.0.0; extra == "dev"
Requires-Dist: flake8>=6.0.0; extra == "dev"
Requires-Dist: mypy>=1.0.0; extra == "dev"
Requires-Dist: isort>=5.12.0; extra == "dev"
Requires-Dist: bump2version>=1.0.0; extra == "dev"
